ipython_blocking/__init__.py
ipython_blocking/ipython_blocking.py
ipython_blocking/ipython_magic.py
ipython_blocking-0.3.1.dist-info/LICENSE
ipython_blocking-0.3.1.dist-info/METADATA
ipython_blocking-0.3.1.dist-info/WHEEL
ipython_blocking-0.3.1.dist-info/top_level.txt
ipython_blocking-0.3.1.dist-info/RECORD
