Metadata-Version: 2.1
Name: ipython-blocking
Version: 0.3.1
Summary: Context manager for blocking cell execution within a Jupyter notebook
Home-page: https://github.com/kafonek/ipython_blocking
Author: Matt Kafonek
Author-email: kafonek@gmail.com
License: BSD
Platform: UNKNOWN
Classifier: Framework :: IPython
Classifier: Programming Language :: Python
Classifier: Intended Audience :: Developers
Classifier: Development Status :: 3 - Alpha
License-File: LICENSE
Requires-Dist: IPython
Requires-Dist: ipywidgets
Requires-Dist: nbclient
